einvoice/__init__.py
einvoice-0.1.0.dist-info/METADATA
einvoice-0.1.0.dist-info/WHEEL
einvoice-0.1.0.dist-info/top_level.txt
einvoice-0.1.0.dist-info/RECORD
