Metadata-Version: 2.1
Name: einvoice
Version: 0.1.0
Summary: Extract embedded information from einvoice Secure QR Code.
Author: Hemanth Sai
Author-email: mannehemanthsai@gmail.com
Classifier: Programming Language :: Python :: 3
Classifier: License :: OSI Approved :: MIT License
Classifier: Operating System :: OS Independent
Requires-Python: >=3.6
